thefactory/__init__.py
thefactory/_version.py
thefactory/config.py
thefactory/factory_utilities.py
thefactory/google_analytics.py
thefactory/google_configv4.py
thefactory/setup.py
thefactory-1.0.3.dist-info/METADATA
thefactory-1.0.3.dist-info/WHEEL
thefactory-1.0.3.dist-info/top_level.txt
thefactory-1.0.3.dist-info/RECORD
